pndconf/__init__.py
pndconf/__main__.py
pndconf/bibliography.py
pndconf/commands.py
pndconf/compilers.py
pndconf/config.py
pndconf/config_default.ini
pndconf/const.py
pndconf/functions.py
pndconf/parser.py
pndconf/py.typed
pndconf/transforms.py
pndconf/util.py
pndconf/watcher.py
pndconf-0.5.0.dist-info/entry_points.txt
pndconf-0.5.0.dist-info/LICENSE
pndconf-0.5.0.dist-info/WHEEL
pndconf-0.5.0.dist-info/METADATA
pndconf-0.5.0.dist-info/RECORD
